src/ARTAU.v
`timescale 1us / 1ps

module ARTAU(
    input radar_echo,
    input scan_for_target,
    input [31:0] jet_speed,
    input [31:0] max_safe_distance,
    input RST,
    input CLK,
    output reg radar_pulse_trigger,
    output reg [31:0] distance_to_target,
    output reg threat_detected,
    output reg [1:0] ARTAU_state
);
reg run_trigger;

reg[31:0] first_start_time;
reg[31:0] distance_start_time;
reg[31:0] distance_end_time;

reg[31:0] pulse_emition_timer;
reg[31:0] listen_to_echo_timer;
reg[31:0] status_update_timer;
reg[31:0] timevar;

reg[1:0] next_state;
reg[1:0] pulse_counter;


reg[64:0] speed_of_light;
reg[64:0] microsecond;
reg[7:0]  clock_time;

reg[31:0] distance1;
reg[31:0] distance2;
reg signed [32:0] relative_distance;

initial begin
    timevar = 0;
    pulse_counter = 0;
    pulse_emition_timer = 0;
    listen_to_echo_timer = 0;
    status_update_timer = 0;
    next_state = 0;
    radar_pulse_trigger = 0;
    speed_of_light = 300000000; // m/s
    microsecond = 1000000; // us
    clock_time = 50; // us
end



always @(posedge CLK or negedge CLK) begin
    //$display(timevar);
    timevar = timevar + 1;

    case (ARTAU_state)

            0:begin
                pulse_counter = 0;
            end

            1:begin
                if (timevar - pulse_emition_timer > 6) begin
                    run_trigger = 1;
                end

            end

            2:begin
                if (timevar -listen_to_echo_timer >= 40) begin
                    run_trigger = 1;
                end
            end

            3:begin
                if (timevar - status_update_timer >= 60) begin
                    run_trigger = 1;
                end
            end

        endcase

end




always@(posedge CLK or posedge RST) begin
    if (RST) begin
        radar_pulse_trigger = 0;
        distance_to_target = 0;
        threat_detected = 0;
        ARTAU_state = 0;
        next_state = 0;
    end else begin
        ARTAU_state = next_state;
    end 
end

always @(posedge radar_echo or posedge scan_for_target or posedge run_trigger) begin
    run_trigger = 0;

    case (ARTAU_state)

    0:begin
        if(scan_for_target) begin
            
            pulse_emition_timer = timevar;
            radar_pulse_trigger = 1;
            next_state = 1; // EMIT
        end
    end

    1:begin
        if (radar_pulse_trigger) begin

            if(timevar -pulse_emition_timer > 6) begin
                pulse_counter = pulse_counter + 1;
                radar_pulse_trigger = 0;
                pulse_emition_timer = 0;

                distance_start_time = $realtime;
                listen_to_echo_timer = timevar;
                //$display("pulse_emition_timer: %d", timevar- pulse_emition_timer, " pulse_counter: %d", pulse_counter , " listen_to_echo_timer: ", listen_to_echo_timer);
                next_state = 2; // LISTEN
                
            end
        end
    end

    2:begin
        distance_end_time = $realtime;
        if ((timevar - listen_to_echo_timer) < 40) begin
            if(radar_echo) begin

                distance_end_time = $realtime;
                //$display("distance_end_time: %d", distance_end_time, " distance_start_time: %d", distance_start_time, " distance_to_target: ", distance_to_target);

                if(pulse_counter == 1) begin
                    first_start_time = distance_start_time;
                    radar_pulse_trigger = 1;
                    pulse_emition_timer = timevar;
                    next_state = 1;
                    
                    distance1 = ((distance_end_time - distance_start_time) *speed_of_light) / (2 * microsecond);
                    distance_to_target = distance1;
                    //$display("distance_end_time: %d", distance_end_time, " distance_start_time: %d", distance_start_time, " distance_to_target: ", distance_to_target);
                
                end else if (pulse_counter == 2) begin

                    
                    status_update_timer = timevar;
                    next_state = 3;

                    distance2 = ((distance_end_time - distance_start_time) *speed_of_light) / (2 * microsecond);
                    distance_to_target = distance2;

                    //$display("distance_end_time: %d", distance_end_time, " distance_start_time: %d", distance_start_time, " distance_to_target: ", distance_to_target);
                    relative_distance = (distance2 + ((jet_speed*(distance_end_time- first_start_time))/microsecond) - distance1);


                    //$display("relative_distance:" , relative_distance);
                    if (max_safe_distance > distance2 && relative_distance < 0) begin
                        threat_detected = 1;
                    end else begin
                        threat_detected = 0;
                    end

                    
                end

                listen_to_echo_timer = timevar;
            end

        end else begin
            threat_detected = 0;
            distance_to_target = 0;
            next_state = 0;
        end

    end

    3:begin
        pulse_counter = 0;
        if(timevar- status_update_timer < 60 || scan_for_target) begin
            if(scan_for_target) begin
                pulse_emition_timer = timevar;
                radar_pulse_trigger = 1;
                next_state = 1; // EMIT
            end
        end else begin
            threat_detected = 0;
            distance_to_target = 0;
            next_state = 0;
        end
    end

    endcase
end

endmodule

src/ARTAU_tb.v
`timescale 1us / 1ns

module ARTAU_tb;

    // Inputs
    reg radar_echo;
    reg scan_for_target;
    reg [31:0] jet_speed;
    reg [31:0] max_safe_distance;
    reg RST;
    reg CLK;

    // Outputs
    wire radar_pulse_trigger;
    wire [31:0] distance_to_target;
    wire threat_detected;
    wire [1:0] ARTAU_state;

    // Clock generation
    initial begin
        CLK = 0;
        forever #50 CLK = ~CLK; 
    end

    // Instantiate the Unit Under Test (UUT)
    ARTAU uut(
        .radar_echo(radar_echo),
        .scan_for_target(scan_for_target),
        .jet_speed(jet_speed),
        .max_safe_distance(max_safe_distance),
        .RST(RST),
        .CLK(CLK),
        .radar_pulse_trigger(radar_pulse_trigger),
        .distance_to_target(distance_to_target),
        .threat_detected(threat_detected),
        .ARTAU_state(ARTAU_state)
    );

    // Dump to waveform file
    initial begin
        $dumpfile("ARTAU.vcd");
        $dumpvars;
    end

    initial begin

        // Initialize Inputs
        RST = 1;
        radar_echo = 0;
        scan_for_target = 0;
        jet_speed = 0;
        max_safe_distance = 0;
        max_safe_distance = 20000;
        jet_speed = 7000;
        
        // Reset the system
        #100;
        RST = 0;
        #200;

        // Stimulus
        scan_for_target = 1;
        #25;
        scan_for_target = 0;
        #25;
        #250; 
        #50;
        #50;
        radar_echo = 1;
        #2;
        radar_echo = 0;
        #347;
        radar_echo = 1;
        #2;
        radar_echo = 0;
        #98;
        #3100;
        scan_for_target = 1;
        #50;
        scan_for_target = 0;
        #400;
        radar_echo = 1;
        #10;
        radar_echo = 0;
        #500;
        radar_echo = 1;
        #10;
        radar_echo = 0;
        #300;
        scan_for_target = 1;
        #150;
        scan_for_target = 0;
        #2300;
        scan_for_target = 1;
        #50;
        scan_for_target = 0;
        #600;
        RST=1;
        #100;
        RST=0;
        #100;

        // End the simulation
        $finish;
    end

endmodule

src/ARTAU.vcd
$date
	Sat Jan 13 16:34:10 2024
$end
$version
	Icarus Verilog
$end
$timescale
	1ps
$end
$scope module ARTAU_tb $end
$var wire 1 ! threat_detected $end
$var wire 1 " radar_pulse_trigger $end
$var wire 32 # distance_to_target [31:0] $end
$var wire 2 $ ARTAU_state [1:0] $end
$var reg 1 % CLK $end
$var reg 1 & RST $end
$var reg 32 ' jet_speed [31:0] $end
$var reg 32 ( max_safe_distance [31:0] $end
$var reg 1 ) radar_echo $end
$var reg 1 * scan_for_target $end
$scope module uut $end
$var wire 1 % CLK $end
$var wire 1 & RST $end
$var wire 32 + jet_speed [31:0] $end
$var wire 32 , max_safe_distance [31:0] $end
$var wire 1 ) radar_echo $end
$var wire 1 * scan_for_target $end
$var reg 2 - ARTAU_state [1:0] $end
$var reg 8 . clock_time [7:0] $end
$var reg 32 / distance1 [31:0] $end
$var reg 32 0 distance2 [31:0] $end
$var reg 32 1 distance_end_time [31:0] $end
$var reg 32 2 distance_start_time [31:0] $end
$var reg 32 3 distance_to_target [31:0] $end
$var reg 32 4 first_start_time [31:0] $end
$var reg 32 5 listen_to_echo_timer [31:0] $end
$var reg 65 6 microsecond [64:0] $end
$var reg 2 7 next_state [1:0] $end
$var reg 2 8 pulse_counter [1:0] $end
$var reg 32 9 pulse_emition_timer [31:0] $end
$var reg 1 " radar_pulse_trigger $end
$var reg 33 : relative_distance [32:0] $end
$var reg 1 ; run_trigger $end
$var reg 65 < speed_of_light [64:0] $end
$var reg 32 = status_update_timer [31:0] $end
$var reg 1 ! threat_detected $end
$var reg 32 > timevar [31:0] $end
$upscope $end
$upscope $end
$enddefinitions $end
$comment Show the parameter values. $end
$dumpall
$end
#0
$dumpvars
b1 >
b0 =
b10001111000011010001100000000 <
x;
bx :
b0 9
b0 8
b0 7
b11110100001001000000 6
b0 5
bx 4
b0 3
bx 2
bx 1
bx 0
bx /
b110010 .
b0 -
b100111000100000 ,
b1101101011000 +
0*
0)
b100111000100000 (
b1101101011000 '
1&
0%
b0 $
b0 #
0"
0!
$end
#50000000
b10 >
1%
#100000000
b11 >
0%
0&
#150000000
b100 >
1%
#200000000
b101 >
0%
#250000000
b110 >
1%
#300000000
b111 >
b1 7
1"
b110 9
0;
0%
1*
#325000000
0*
#350000000
b1 $
b1 -
b1000 >
1%
#400000000
b1001 >
0%
#450000000
b1010 >
1%
#500000000
b1011 >
0%
#550000000
b1100 >
1%
#600000000
b10 7
b1101 5
b1001011000 2
b0 9
0"
b1 8
0;
b1101 >
0%
#650000000
b1010001010 1
b10 $
b10 -
0;
b1110 >
1%
#700000000
b1111 >
b1110 5
b11101010011000 #
b11101010011000 3
b11101010011000 /
b1 7
b1110 9
1"
b1001011000 4
b1010111100 1
0%
1)
#702000000
0)
#750000000
b1 $
b1 -
b10000 >
1%
#800000000
b10001 >
0%
#850000000
b10010 >
1%
#900000000
b10011 >
0%
#950000000
b10100 >
1%
#1000000000
b10 7
b10101 5
b1111101000 2
b0 9
0"
b10 8
0;
b10101 >
0%
#1049000000
1)
#1050000000
b10110 5
1!
b111111111111111111110001010110111 :
b1110101001100 #
b1110101001100 3
b1110101001100 0
b11 7
b10110 =
b10000011010 1
b10 $
b10 -
0;
b10110 >
1%
#1051000000
0)
#1100000000
b10111 >
0%
#1150000000
b11 $
b11 -
b11000 >
1%
#1200000000
b11001 >
0%
#1250000000
b11010 >
1%
#1300000000
b11011 >
0%
#1350000000
b11100 >
1%
#1400000000
b11101 >
0%
#1450000000
b11110 >
1%
#1500000000
b11111 >
0%
#1550000000
b100000 >
1%
#1600000000
b100001 >
0%
#1650000000
b100010 >
1%
#1700000000
b100011 >
0%
#1750000000
b100100 >
1%
#1800000000
b100101 >
0%
#1850000000
b100110 >
1%
#1900000000
b100111 >
0%
#1950000000
b101000 >
1%
#2000000000
b101001 >
0%
#2050000000
b101010 >
1%
#2100000000
b101011 >
0%
#2150000000
b101100 >
1%
#2200000000
b101101 >
0%
#2250000000
b101110 >
1%
#2300000000
b101111 >
0%
#2350000000
b110000 >
1%
#2400000000
b110001 >
0%
#2450000000
b110010 >
1%
#2500000000
b110011 >
0%
#2550000000
b110100 >
1%
#2600000000
b110101 >
0%
#2650000000
b110110 >
1%
#2700000000
b110111 >
0%
#2750000000
b111000 >
1%
#2800000000
b111001 >
0%
#2850000000
b111010 >
1%
#2900000000
b111011 >
0%
#2950000000
b111100 >
1%
#3000000000
b111101 >
0%
#3050000000
b111110 >
1%
#3100000000
b111111 >
0%
#3150000000
b1000000 >
1%
#3200000000
b1000001 >
0%
#3250000000
b1000010 >
1%
#3300000000
b1000011 >
0%
#3350000000
b1000100 >
1%
#3400000000
b1000101 >
0%
#3450000000
b1000110 >
1%
#3500000000
b1000111 >
0%
#3550000000
b1001000 >
1%
#3600000000
b1001001 >
0%
#3650000000
b1001010 >
1%
#3700000000
b1001011 >
0%
#3750000000
b1001100 >
1%
#3800000000
b1001101 >
0%
#3850000000
b1001110 >
1%
#3900000000
b1001111 >
0%
#3950000000
b1010000 >
1%
#4000000000
b1010001 >
0%
#4050000000
b0 7
b0 #
b0 3
0!
b0 8
0;
b1010010 >
1%
#4100000000
0;
b1010011 >
0%
#4150000000
b0 $
b0 -
0;
b1010100 >
1%
#4200000000
b1010101 >
0%
#4249000000
b1 7
1"
b1010101 9
1*
#4250000000
b1 $
b1 -
b1010110 >
1%
#4299000000
0*
#4300000000
b1010111 >
0%
#4350000000
b1011000 >
1%
#4400000000
b1011001 >
0%
#4450000000
b1011010 >
1%
#4500000000
b1011011 >
0%
#4550000000
b10 7
b1011100 5
b1000111000110 2
b0 9
0"
b1 8
0;
b1011100 >
1%
#4600000000
0;
b1011101 >
0%
#4650000000
b1001000101010 1
b10 $
b10 -
0;
b1011110 >
1%
#4699000000
b1011110 5
b101011101001110 #
b101011101001110 3
b101011101001110 /
b1 7
b1011110 9
1"
b1000111000110 4
b1001001011011 1
1)
#4700000000
b1011111 >
0%
#4709000000
0)
#4750000000
b1 $
b1 -
b1100000 >
1%
#4800000000
b1100001 >
0%
#4850000000
b1100010 >
1%
#4900000000
b1100011 >
0%
#4950000000
b1100100 >
1%
#5000000000
b10 7
b1100101 5
b1001110001000 2
b0 9
0"
b10 8
0;
b1100101 >
0%
#5050000000
b1001110111010 1
b10 $
b10 -
0;
b1100110 >
1%
#5100000000
b1100111 >
0%
#5150000000
b1101000 >
1%
#5200000000
b1101001 >
0%
#5209000000
b1101001 5
b10001100101100 :
b111101001110110 #
b111101001110110 3
b111101001110110 0
b11 7
b1101001 =
b1010001011001 1
1)
#5219000000
0)
#5250000000
b11 $
b11 -
b1101010 >
1%
#5300000000
b1101011 >
0%
#5350000000
b1101100 >
1%
#5400000000
b1101101 >
0%
#5450000000
b1101110 >
1%
#5500000000
b1101111 >
0%
#5519000000
b1 7
1"
b1101111 9
b0 8
1*
#5550000000
b1 $
b1 -
b1110000 >
1%
#5600000000
b1110001 >
0%
#5650000000
b1110010 >
1%
#5669000000
0*
#5700000000
b1110011 >
0%
#5750000000
b1110100 >
1%
#5800000000
b1110101 >
0%
#5850000000
b10 7
b1110110 5
b1011011011010 2
b0 9
0"
b1 8
0;
b1110110 >
1%
#5900000000
0;
b1110111 >
0%
#5950000000
b1011100111110 1
b10 $
b10 -
0;
b1111000 >
1%
#6000000000
b1111001 >
0%
#6050000000
b1111010 >
1%
#6100000000
b1111011 >
0%
#6150000000
b1111100 >
1%
#6200000000
b1111101 >
0%
#6250000000
b1111110 >
1%
#6300000000
b1111111 >
0%
#6350000000
b10000000 >
1%
#6400000000
b10000001 >
0%
#6450000000
b10000010 >
1%
#6500000000
b10000011 >
0%
#6550000000
b10000100 >
1%
#6600000000
b10000101 >
0%
#6650000000
b10000110 >
1%
#6700000000
b10000111 >
0%
#6750000000
b10001000 >
1%
#6800000000
b10001001 >
0%
#6850000000
b10001010 >
1%
#6900000000
b10001011 >
0%
#6950000000
b10001100 >
1%
#7000000000
b10001101 >
0%
#7050000000
b10001110 >
1%
#7100000000
b10001111 >
0%
#7150000000
b10010000 >
1%
#7200000000
b10010001 >
0%
#7250000000
b10010010 >
1%
#7300000000
b10010011 >
0%
#7350000000
b10010100 >
1%
#7400000000
b10010101 >
0%
#7450000000
b10010110 >
1%
#7500000000
b10010111 >
0%
#7550000000
b10011000 >
1%
#7600000000
b10011001 >
0%
#7650000000
b10011010 >
1%
#7700000000
b10011011 >
0%
#7750000000
b10011100 >
1%
#7800000000
b10011101 >
0%
#7850000000
b0 7
b0 #
b0 3
b1111010101010 1
0;
b10011110 >
1%
#7900000000
b1111011011100 1
0;
b10011111 >
0%
#7950000000
b0 $
b0 -
0;
b10100000 >
1%
#7969000000
b1 7
1"
b10100000 9
1*
#8000000000
b0 8
b10100001 >
0%
#8019000000
0*
#8050000000
b1 $
b1 -
b10100010 >
1%
#8100000000
b10100011 >
0%
#8150000000
b10100100 >
1%
#8200000000
b10100101 >
0%
#8250000000
b10100110 >
1%
#8300000000
b10 7
b10100111 5
b10000001101100 2
b0 9
0"
b1 8
0;
b10100111 >
0%
#8350000000
b10000010011110 1
b10 $
b10 -
0;
b10101000 >
1%
#8400000000
b10101001 >
0%
#8450000000
b10101010 >
1%
#8500000000
b10101011 >
0%
#8550000000
b10101100 >
1%
#8600000000
b10101101 >
0%
#8619000000
b0 7
b0 $
b0 -
1&
#8650000000
b0 8
b10101110 >
1%
#8700000000
b10101111 >
0%
#8719000000
0&
#8750000000
b10110000 >
1%
#8800000000
b10110001 >
0%
