src/ARTAU.v
`timescale 1us / 1ps

module ARTAU(
    input radar_echo,
    input scan_for_target,
    input [31:0] jet_speed,
    input [31:0] max_safe_distance,
    input RST,
    input CLK,
    output reg radar_pulse_trigger,
    output reg [31:0] distance_to_target,
    output reg threat_detected,
    output reg [1:0] ARTAU_state
);

reg innerCLK;

reg echo_waits;
reg echo_trigger;

reg[31:0] first_start_time;
reg[31:0] distance_start_time;
reg[31:0] distance_end_time;

reg[31:0] pulse_timer_start;
reg[31:0] listen_timer_start;
reg[31:0] asses_timer_start;

reg[1:0] next_state;
reg[1:0] pulse_counter;

reg[31:0] pulse_time;
reg[31:0] listen_time;
reg[31:0] asses_time;

reg[64:0] speed_of_light;
reg[64:0] microsecond;
reg[7:0]  clock_time;

reg[31:0] distance1;
reg[31:0] distance2;
reg signed [32:0] relative_distance;

initial begin
    innerCLK = 0;
    pulse_counter = 0;
    next_state = 0;
    radar_pulse_trigger = 0;
    speed_of_light = 300000000; // m/s
    microsecond = 1000000; // us
    clock_time = 50; // us

    pulse_time = 300; // us
    listen_time = 2000; // us
    asses_time = 3000; // us

    forever innerCLK = #1 ~innerCLK;
end



always @(posedge radar_echo or posedge echo_trigger) begin
    //$display("RADAR ECHO ", radar_echo, " ARTAU STATE ", ARTAU_state, " next_state ", $realtime - pulse_timer_start);

    case(ARTAU_state)
        2:begin // IDLE STATE
            echo_waits = 0;
            distance_end_time = $realtime;

            if(pulse_counter == 1) begin
                first_start_time = distance_start_time;
                distance1 = ((distance_end_time - distance_start_time) *speed_of_light) / (2 * microsecond);
                distance_to_target = distance1;

                radar_pulse_trigger = 1;
                pulse_timer_start = $realtime;
                next_state = 1; // EMIT STATE
            end else if (pulse_counter  == 2) begin
                distance2 = ((distance_end_time - distance_start_time) *speed_of_light) / (2 * microsecond);
                distance_to_target = distance2;

                relative_distance = (distance2 + ((jet_speed*(distance_end_time- first_start_time))/microsecond) - distance1);
                //$display("DISTANCE 1 ", distance1, " DISTANCE 2 ", distance2, " RELATIVE DISTANCE ", relative_distance);
                if (max_safe_distance > distance2 && relative_distance < 0) begin
                    threat_detected = 1;
                end else begin
                    threat_detected = 0;
                end

                asses_timer_start = $realtime;
                next_state = 3; // ASSESS STATE
            end 
        end

        default:begin
            echo_waits = 1;
        end

    endcase
end

always @(posedge scan_for_target) begin
    //$display("SCAN FOR TARGET ", scan_for_target, " ARTAU STATE ", ARTAU_state, " ", next_state, " ", $realtime);
    case(ARTAU_state)

        0:begin // IDLE STATE
            pulse_timer_start = $realtime;
            pulse_counter = 0;
            radar_pulse_trigger = 1;
            #10;
            next_state = 1; // EMIT STATE
        end

        3: begin // ASSESS STATE
            pulse_timer_start = $realtime;
            pulse_counter = 0;
            radar_pulse_trigger = 1;
            #10;
            next_state = 1; // EMIT STATE
        end

    endcase
end

always @(posedge CLK) begin
    ARTAU_state = next_state;
end


always @(innerCLK) begin
    //$display("ALL");
    case(ARTAU_state)
            1:begin 
                if (radar_pulse_trigger) begin
                    if ($realtime - pulse_timer_start >= pulse_time) begin
                        
                        radar_pulse_trigger = 0;
                        pulse_counter = pulse_counter + 1;

                        listen_timer_start = $realtime;
                        distance_start_time = listen_timer_start;
                        
                        next_state = 2; // LISTEN STATE
                        
                    end
                end
            end
            
            2: begin
                
                if ($realtime - listen_timer_start >= listen_time) begin
                    distance_to_target = 0;
                    next_state = 0; // IDLE STATE
                end else begin
                    if (echo_waits) begin
                        echo_trigger = 1;
                    end
                end
            end

            3: begin // ASSESS STATE
                if ($realtime - asses_timer_start >= asses_time) begin
                    distance_to_target = 0;
                    next_state = 0; // IDLE STATE
                end 
            end

        endcase
end

always @(posedge RST) begin
    if (RST) begin
        radar_pulse_trigger = 0;
        distance_to_target = 0;
        threat_detected = 0;
        ARTAU_state = 0;
        next_state = 0;
    end
end


endmodule

src/ARTAU_tb.v
`timescale 1us / 1ns

module ARTAU_tb;

    // Inputs
    reg radar_echo;
    reg scan_for_target;
    reg [31:0] jet_speed;
    reg [31:0] max_safe_distance;
    reg RST;
    reg CLK;

    // Outputs
    wire radar_pulse_trigger;
    wire [31:0] distance_to_target;
    wire threat_detected;
    wire [1:0] ARTAU_state;

    // Clock generation
    initial begin
        CLK = 0;
        forever #50 CLK = ~CLK; 
    end

    // Instantiate the Unit Under Test (UUT)
    ARTAU uut(
        .radar_echo(radar_echo),
        .scan_for_target(scan_for_target),
        .jet_speed(jet_speed),
        .max_safe_distance(max_safe_distance),
        .RST(RST),
        .CLK(CLK),
        .radar_pulse_trigger(radar_pulse_trigger),
        .distance_to_target(distance_to_target),
        .threat_detected(threat_detected),
        .ARTAU_state(ARTAU_state)
    );

    // Dump to waveform file
    initial begin
        $dumpfile("ARTAU.vcd");
        $dumpvars;
    end

    initial begin

        // Initialize Inputs
        RST = 1;
        radar_echo = 0;
        scan_for_target = 0;
        jet_speed = 0;
        max_safe_distance = 0;
        max_safe_distance = 20000;
        jet_speed = 7000;
        
        // Reset the system
        #100;
        RST = 0;
        #200;

        // Stimulus
        scan_for_target = 1;
        #25;
        scan_for_target = 0;
        #25;
        #250; 
        #50;
        #50;
        radar_echo = 1;
        #2;
        radar_echo = 0;
        #347;
        radar_echo = 1;
        #2;
        radar_echo = 0;
        #98;
        #3100;
        scan_for_target = 1;
        #50;
        scan_for_target = 0;
        #400;
        radar_echo = 1;
        #10;
        radar_echo = 0;
        #500;
        radar_echo = 1;
        #10;
        radar_echo = 0;
        #300;
        scan_for_target = 1;
        #150;
        scan_for_target = 0;
        #2300;
        scan_for_target = 1;
        #50;
        scan_for_target = 0;
        #600;
        RST=1;
        #100;
        RST=0;
        #100;

        // End the simulation
        $finish;
    end

endmodule

src/ARTAU.vcd
$date
	Sat Jan 13 23:57:39 2024
$end
$version
	Icarus Verilog
$end
$timescale
	1ps
$end
$scope module ARTAU_tb $end
$var wire 1 ! threat_detected $end
$var wire 1 " radar_pulse_trigger $end
$var wire 32 # distance_to_target [31:0] $end
$var wire 2 $ ARTAU_state [1:0] $end
$var reg 1 % CLK $end
$var reg 1 & RST $end
$var reg 32 ' jet_speed [31:0] $end
$var reg 32 ( max_safe_distance [31:0] $end
$var reg 1 ) radar_echo $end
$var reg 1 * scan_for_target $end
$scope module uut $end
$var wire 1 % CLK $end
$var wire 1 & RST $end
$var wire 32 + jet_speed [31:0] $end
$var wire 32 , max_safe_distance [31:0] $end
$var wire 1 ) radar_echo $end
$var wire 1 * scan_for_target $end
$var reg 2 - ARTAU_state [1:0] $end
$var reg 32 . asses_time [31:0] $end
$var reg 32 / asses_timer_start [31:0] $end
$var reg 8 0 clock_time [7:0] $end
$var reg 32 1 distance1 [31:0] $end
$var reg 32 2 distance2 [31:0] $end
$var reg 32 3 distance_end_time [31:0] $end
$var reg 32 4 distance_start_time [31:0] $end
$var reg 32 5 distance_to_target [31:0] $end
$var reg 1 6 echo_trigger $end
$var reg 1 7 echo_waits $end
$var reg 32 8 first_start_time [31:0] $end
$var reg 1 9 innerCLK $end
$var reg 32 : listen_time [31:0] $end
$var reg 32 ; listen_timer_start [31:0] $end
$var reg 65 < microsecond [64:0] $end
$var reg 2 = next_state [1:0] $end
$var reg 2 > pulse_counter [1:0] $end
$var reg 32 ? pulse_time [31:0] $end
$var reg 32 @ pulse_timer_start [31:0] $end
$var reg 1 " radar_pulse_trigger $end
$var reg 33 A relative_distance [32:0] $end
$var reg 65 B speed_of_light [64:0] $end
$var reg 1 ! threat_detected $end
$upscope $end
$upscope $end
$enddefinitions $end
$comment Show the parameter values. $end
$dumpall
$end
#0
$dumpvars
b10001111000011010001100000000 B
bx A
bx @
b100101100 ?
b0 >
b0 =
b11110100001001000000 <
bx ;
b11111010000 :
09
bx 8
x7
x6
b0 5
bx 4
bx 3
bx 2
bx 1
b110010 0
bx /
b101110111000 .
b0 -
b100111000100000 ,
b1101101011000 +
0*
0)
b100111000100000 (
b1101101011000 '
1&
0%
b0 $
b0 #
0"
0!
$end
#5000000
19
#10000000
09
#15000000
19
#20000000
09
#25000000
19
#30000000
09
#35000000
19
#40000000
09
#45000000
19
#50000000
09
1%
#55000000
19
#60000000
09
#65000000
19
#70000000
09
#75000000
19
#80000000
09
#85000000
19
#90000000
09
#95000000
19
#100000000
09
0%
0&
#105000000
19
#110000000
09
#115000000
19
#120000000
09
#125000000
19
#130000000
09
#135000000
19
#140000000
09
#145000000
19
#150000000
09
1%
#155000000
19
#160000000
09
#165000000
19
#170000000
09
#175000000
19
#180000000
09
#185000000
19
#190000000
09
#195000000
19
#200000000
09
0%
#205000000
19
#210000000
09
#215000000
19
#220000000
09
#225000000
19
#230000000
09
#235000000
19
#240000000
09
#245000000
19
#250000000
09
1%
#255000000
19
#260000000
09
#265000000
19
#270000000
09
#275000000
19
#280000000
09
#285000000
19
#290000000
09
#295000000
19
#300000000
1"
b100101100 @
09
0%
1*
#305000000
19
#310000000
09
b1 =
#315000000
19
#320000000
09
#325000000
19
0*
#330000000
09
#335000000
19
#340000000
09
#345000000
19
#350000000
b1 $
b1 -
09
1%
#355000000
19
#360000000
09
#365000000
19
#370000000
09
#375000000
19
#380000000
09
#385000000
19
#390000000
09
#395000000
19
#400000000
09
0%
#405000000
19
#410000000
09
#415000000
19
#420000000
09
#425000000
19
#430000000
09
#435000000
19
#440000000
09
#445000000
19
#450000000
09
1%
#455000000
19
#460000000
09
#465000000
19
#470000000
09
#475000000
19
#480000000
09
#485000000
19
#490000000
09
#495000000
19
#500000000
09
0%
#505000000
19
#510000000
09
#515000000
19
#520000000
09
#525000000
19
#530000000
09
#535000000
19
#540000000
09
#545000000
19
#550000000
09
1%
#555000000
19
#560000000
09
#565000000
19
#570000000
09
#575000000
19
#580000000
09
#585000000
19
#590000000
09
#595000000
19
#600000000
b10 =
b1001011000 4
b1001011000 ;
b1 >
0"
09
0%
#605000000
19
#610000000
09
#615000000
19
#620000000
09
#625000000
19
#630000000
09
#635000000
19
#640000000
09
#645000000
19
#650000000
b10 $
b10 -
09
1%
#655000000
19
#660000000
09
#665000000
19
#670000000
09
#675000000
19
#680000000
09
#685000000
19
#690000000
09
#695000000
19
#700000000
b1 =
b1010111100 @
1"
b11101010011000 #
b11101010011000 5
b11101010011000 1
b1010111100 3
07
09
0%
1)
#702000000
0)
#705000000
19
#710000000
09
#715000000
19
#720000000
09
#725000000
19
#730000000
09
#735000000
19
#740000000
09
#745000000
19
#750000000
b1 $
b1 -
09
1%
