src/ECSU.v
`timescale 1us / 1ps

module ECSU(
    input CLK,
    input RST,
    input thunderstorm,
    input [5:0] wind,
    input [1:0] visibility,
    input signed [7:0] temperature,
    output reg severe_weather,
    output reg emergency_landing_alert,
    output reg [1:0] ECSU_state
);

always @(posedge CLK or posedge RST or negedge CLK) begin
    if (RST) begin
        severe_weather <= 0;
        emergency_landing_alert <= 0;
        ECSU_state <= 0;
    end
    else begin
        case (ECSU_state)
            0: begin
                if ((wind > 10 && wind <= 15) || (visibility == 1)) begin
                    severe_weather <= 0;
                    emergency_landing_alert <= 0;
                    if (CLK == 1) begin
                        ECSU_state <= 1;
                    end
                end
                else if (thunderstorm || temperature < -35 || temperature > 35 || wind > 15 || visibility == 3) begin
                    emergency_landing_alert <= 0;
                    severe_weather <= 1;
                    if (CLK == 1) begin
                        ECSU_state <= 2;
                    end
                end
                else begin
                    if (CLK == 1) begin
                        ECSU_state <= 0;
                    end
                end 
            end

            1: begin
                if (wind <= 10 && visibility == 0) begin  
                    severe_weather <= 0;
                    emergency_landing_alert <= 0;
                    if (CLK == 1) begin
                        ECSU_state <= 0;
                    end
                end 
                else if (thunderstorm || temperature < -35 || temperature > 35 || wind > 15 || visibility == 3) begin
                    emergency_landing_alert <= 0;
                    severe_weather <= 1;
                    if (CLK == 1) begin
                        ECSU_state <= 2;
                    end
                end
                else begin
                    if (CLK == 1) begin
                        ECSU_state <= 1;
                    end
                end
            end

            2: begin
                
                
                if (temperature < -40 || temperature > 40 || wind > 20) begin
                    severe_weather <= 1;
                    emergency_landing_alert <= 1;
                    if (CLK == 1) begin
                        ECSU_state <= 3;
                    end
                end
                else if(thunderstorm == 0 && wind <=10 && (temperature >= -35 && temperature <=35) && visibility == 1) begin
                    severe_weather <= 0;
                    emergency_landing_alert <= 0;
                    if (CLK == 1) begin
                        ECSU_state <= 1;
                    end
                end
                else begin
                    if (CLK == 1) begin
                        ECSU_state <= 2;
                    end
                end
            end

            3: begin
                //emergency_landing_alert <= 1;
                // No state change
            end

            default: begin
                // Hata durumu, burada gerekirse çıkışları güncelleyebilirsiniz.
            end
        endcase
    end
end


endmodule

src/ECSU_2_tb.v
`timescale 1us / 1ns

module ECSU_tb;

    // Inputs
    reg CLK;
    reg RST;
    reg thunderstorm;
    reg [5:0] wind;
    reg [1:0] visibility;
    reg signed [7:0] temp;
    
    // Outputs
    wire severe_weather;
    wire emergency_landing_alert;
    wire [1:0] ECSU_state; 
    
    // Instantiate the Unit Under Test (UUT)
    ECSU uut (
        .CLK(CLK),
        .RST(RST),
        .thunderstorm(thunderstorm),
        .wind(wind),
        .visibility(visibility),
        .temperature(temp),
        .severe_weather(severe_weather),
        .emergency_landing_alert(emergency_landing_alert),
        .ECSU_state(ECSU_state)
    );
    
    // Clock generation
    initial begin
        CLK = 0;
        forever #50 CLK = ~CLK; 
    end
    
    // Dump to waveform file
    initial begin
        $dumpfile("ECSU.vcd");
        $dumpvars(0, ECSU_tb);
    end

    // Function to print values
    task print_values;
        begin
            $display("Time=%t - RST=%b, thunderstorm=%b, wind=%0d, visibility=%0d, temp=%0d, severe_weather=%b, emergency_landing_alert=%b, ECSU_state=%0d",
                      $time, RST, thunderstorm, wind, visibility, temp, severe_weather, emergency_landing_alert, ECSU_state);
        end
    endtask
    
    initial begin
    
        // Initialize Inputs
        RST = 1;
        thunderstorm = 0;
        wind = 0;
        visibility = 2'b00;
        temp = 0;
        
        // Reset the system
        #100;
        RST = 0;
        #200;
        
        // Stimulus
        thunderstorm = 0; wind = 12; visibility = 2'b00; temp = 25;
        #300; print_values();
        thunderstorm = 0; wind = 5; visibility = 2'b00; temp = 25;
        #300; print_values();
        thunderstorm = 0; wind = 5; visibility = 2'b01; temp = 25;
        #300; print_values();
        thunderstorm = 0; wind = 5; visibility = 2'b00; temp = 25;
        #300; print_values();
        thunderstorm = 0; wind = 5; visibility = 2'b01; temp = 25;
        #300; print_values();
        thunderstorm = 1; wind = 5; visibility = 2'b01; temp = 25;
        #0;   print_values();
        #300; print_values();
        thunderstorm = 0; wind = 5; visibility = 2'b01; temp = 25;
        #300; print_values();
        wind = 3; visibility = 2'b00; temp = -5;
        #300; print_values();
        visibility = 2'b11; 
        #300; print_values();
        wind = 25; visibility = 2'b10;
        #500; print_values();
        thunderstorm = 0; wind = 0; visibility = 2'b00; temp = 0; 
        #200; print_values();
        RST = 1;
        #150; print_values();
        RST = 0;
        #300; print_values();
        thunderstorm = 0; wind = 5; visibility = 2'b01; temp = 25;
        #300; print_values();
        thunderstorm = 0; wind = 15; visibility = 2'b01; 
        #30;  print_values();
        temp = 40;
        #0;   print_values();
        #300; print_values();
        thunderstorm = 0; wind = 5; visibility = 2'b01; temp = 25;
        #300; print_values();
        thunderstorm = 0; wind = 25; visibility = 2'b01; temp = -40;
        #0;   print_values();
        #600; print_values();
        
        // End the simulation
        $finish; 
    end

endmodule

src/ECSU.vcd
$date
	Fri Jan 12 19:24:53 2024
$end
$version
	Icarus Verilog
$end
$timescale
	1ps
$end
$scope module ECSU_tb $end
$var wire 1 ! severe_weather $end
$var wire 1 " emergency_landing_alert $end
$var wire 2 # ECSU_state [1:0] $end
$var reg 1 $ CLK $end
$var reg 1 % RST $end
$var reg 8 & temp [7:0] $end
$var reg 1 ' thunderstorm $end
$var reg 2 ( visibility [1:0] $end
$var reg 6 ) wind [5:0] $end
$scope module uut $end
$var wire 1 $ CLK $end
$var wire 1 % RST $end
$var wire 8 * temperature [7:0] $end
$var wire 1 ' thunderstorm $end
$var wire 2 + visibility [1:0] $end
$var wire 6 , wind [5:0] $end
$var reg 2 - ECSU_state [1:0] $end
$var reg 1 " emergency_landing_alert $end
$var reg 1 ! severe_weather $end
$upscope $end
$scope task print_values $end
$upscope $end
$upscope $end
$enddefinitions $end
$comment Show the parameter values. $end
$dumpall
$end
#0
$dumpvars
b0 -
b0 ,
b0 +
b0 *
b0 )
b0 (
0'
b0 &
1%
0$
b0 #
0"
0!
$end
#50000000
1$
#100000000
0$
0%
#150000000
1$
#200000000
0$
#250000000
1$
#300000000
0$
b11001 &
b11001 *
b1100 )
b1100 ,
#350000000
b1 #
b1 -
1$
#400000000
0$
#450000000
1$
#500000000
0$
#550000000
1$
#600000000
0$
b101 )
b101 ,
#650000000
b0 #
b0 -
1$
#700000000
0$
#750000000
1$
#800000000
0$
#850000000
1$
#900000000
0$
b1 (
b1 +
#950000000
b1 #
b1 -
1$
#1000000000
0$
#1050000000
1$
#1100000000
0$
#1150000000
1$
#1200000000
0$
b0 (
b0 +
#1250000000
b0 #
b0 -
1$
#1300000000
0$
#1350000000
1$
#1400000000
0$
#1450000000
1$
#1500000000
0$
b1 (
b1 +
#1550000000
b1 #
b1 -
1$
#1600000000
0$
#1650000000
1$
#1700000000
0$
#1750000000
1$
#1800000000
1!
0$
1'
#1850000000
b10 #
b10 -
1$
#1900000000
0$
#1950000000
1$
#2000000000
0$
#2050000000
1$
#2100000000
0!
0$
0'
#2150000000
b1 #
b1 -
1$
#2200000000
0$
#2250000000
1$
#2300000000
0$
#2350000000
1$
#2400000000
0$
b11111011 &
b11111011 *
b0 (
b0 +
b11 )
b11 ,
#2450000000
b0 #
b0 -
1$
#2500000000
0$
#2550000000
1$
#2600000000
0$
#2650000000
1$
#2700000000
1!
0$
b11 (
b11 +
#2750000000
b10 #
b10 -
1$
#2800000000
0$
#2850000000
1$
#2900000000
0$
#2950000000
1$
#3000000000
1"
0$
b10 (
b10 +
b11001 )
b11001 ,
#3050000000
b11 #
b11 -
1$
#3100000000
0$
#3150000000
1$
#3200000000
0$
#3250000000
1$
#3300000000
0$
#3350000000
1$
#3400000000
0$
#3450000000
1$
#3500000000
0$
b0 &
b0 *
b0 (
b0 +
b0 )
b0 ,
#3550000000
1$
#3600000000
0$
#3650000000
1$
#3700000000
b0 #
b0 -
0"
0!
0$
1%
#3750000000
1$
#3800000000
0$
#3850000000
1$
0%
#3900000000
0$
#3950000000
1$
#4000000000
0$
#4050000000
1$
#4100000000
0$
#4150000000
b1 #
b1 -
1$
b11001 &
b11001 *
b1 (
b1 +
b101 )
b101 ,
#4200000000
0$
#4250000000
1$
#4300000000
0$
#4350000000
1$
#4400000000
0$
#4450000000
1$
b1111 )
b1111 ,
#4480000000
b101000 &
b101000 *
#4500000000
1!
0$
#4550000000
b10 #
b10 -
1$
#4600000000
0$
#4650000000
1$
#4700000000
0$
#4750000000
1$
#4780000000
b11001 &
b11001 *
b101 )
b101 ,
#4800000000
0!
0$
#4850000000
b1 #
b1 -
1$
#4900000000
0$
#4950000000
1$
#5000000000
0$
#5050000000
1$
#5080000000
b11011000 &
b11011000 *
b11001 )
b11001 ,
#5100000000
1!
0$
#5150000000
b10 #
b10 -
1$
#5200000000
1"
0$
#5250000000
b11 #
b11 -
1$
