src/ECSU.v
`timescale 1us / 1ps

module ECSU(
    input CLK,
    input RST,
    input thunderstorm,
    input [5:0] wind,
    input [1:0] visibility,
    input signed [7:0] temperature,
    output reg severe_weather,
    output reg emergency_landing_alert,
    output reg [1:0] ECSU_state
);

always @(posedge CLK or posedge RST or negedge CLK) begin
    if (RST) begin
        severe_weather <= 0;
        emergency_landing_alert <= 0;
        ECSU_state <= 0;
    end
    else begin
        case (ECSU_state)
            0: begin
                if ((wind > 10 && wind <= 15) || (visibility == 1)) begin
                    severe_weather <= 0;
                    emergency_landing_alert <= 0;
                    if (CLK == 1) begin
                        ECSU_state <= 1;
                    end
                end
                else if (thunderstorm || temperature < -35 || temperature > 35 || wind > 15 || visibility == 3) begin
                    emergency_landing_alert <= 0;
                    severe_weather <= 1;
                    if (CLK == 1) begin
                        ECSU_state <= 2;
                    end
                end
                else begin
                    if (CLK == 1) begin
                        ECSU_state <= 0;
                    end
                end 
            end

            1: begin
                if (wind <= 10 && visibility == 0) begin  
                    severe_weather <= 0;
                    emergency_landing_alert <= 0;
                    if (CLK == 1) begin
                        ECSU_state <= 0;
                    end
                end 
                else if (thunderstorm || temperature < -35 || temperature > 35 || wind > 15 || visibility == 3) begin
                    emergency_landing_alert <= 0;
                    severe_weather <= 1;
                    if (CLK == 1) begin
                        ECSU_state <= 2;
                    end
                end
                else begin
                    if (CLK == 1) begin
                        ECSU_state <= 1;
                    end
                end
            end

            2: begin
                
                
                if (temperature < -40 || temperature > 40 || wind > 20) begin
                    severe_weather <= 1;
                    emergency_landing_alert <= 1;
                    if (CLK == 1) begin
                        ECSU_state <= 3;
                    end
                end
                else if(thunderstorm == 0 && wind <=10 && (temperature >= -35 && temperature <=35) && visibility == 1) begin
                    severe_weather <= 0;
                    emergency_landing_alert <= 0;
                    if (CLK == 1) begin
                        ECSU_state <= 1;
                    end
                end
                else begin
                    if (CLK == 1) begin
                        ECSU_state <= 2;
                    end
                end
            end

            3: begin
                //emergency_landing_alert <= 1;
                // No state change
            end

            default: begin
                // Hata durumu, burada gerekirse çıkışları güncelleyebilirsiniz.
            end
        endcase
    end
end


endmodule

src/ARTAU.v
`timescale 1us / 1ps

module ARTAU(
    input radar_echo,
    input scan_for_target,
    input [31:0] jet_speed,
    input [31:0] max_safe_distance,
    input RST,
    input CLK,
    output reg radar_pulse_trigger,
    output reg [31:0] distance_to_target,
    output reg threat_detected,
    output reg [1:0] ARTAU_state
);

reg innerCLK;

reg echo_waits;
reg echo_trigger;

reg[31:0] first_start_time;
reg[31:0] distance_start_time;
reg[31:0] distance_end_time;

reg[31:0] pulse_timer_start;
reg[31:0] listen_timer_start;
reg[31:0] asses_timer_start;

reg[1:0] next_state;
reg[1:0] pulse_counter;

reg[31:0] pulse_time;
reg[31:0] listen_time;
reg[31:0] asses_time;

reg[64:0] speed_of_light;
reg[64:0] microsecond;
reg[7:0]  clock_time;

reg[31:0] distance1;
reg[31:0] distance2;
reg signed [32:0] relative_distance;

initial begin
    innerCLK = 0;
    pulse_counter = 0;
    next_state = 0;
    radar_pulse_trigger = 0;
    speed_of_light = 300000000; // m/s
    microsecond = 1000000; // us
    clock_time = 50; // us

    pulse_time = 300; // us
    listen_time = 2000; // us
    asses_time = 3000; // us

    forever innerCLK = #1 ~innerCLK;
end



always @(posedge radar_echo or posedge echo_trigger) begin
    //$display("RADAR ECHO ", radar_echo, " ARTAU STATE ", ARTAU_state, " next_state ", $realtime - pulse_timer_start);

    case(ARTAU_state)
        2:begin // IDLE STATE
            echo_waits = 0;
            distance_end_time = $realtime;

            if(pulse_counter == 1) begin
                first_start_time = distance_start_time;
                distance1 = ((distance_end_time - distance_start_time) *speed_of_light) / (2 * microsecond);
                distance_to_target = distance1;

                radar_pulse_trigger = 1;
                pulse_timer_start = $realtime;
                next_state = 1; // EMIT STATE
            end else if (pulse_counter  == 2) begin
                distance2 = ((distance_end_time - distance_start_time) *speed_of_light) / (2 * microsecond);
                distance_to_target = distance2;

                relative_distance = (distance2 + ((jet_speed*(distance_end_time- first_start_time))/microsecond) - distance1);
                //$display("DISTANCE 1 ", distance1, " DISTANCE 2 ", distance2, " RELATIVE DISTANCE ", relative_distance);
                if (max_safe_distance > distance2 && relative_distance < 0) begin
                    threat_detected = 1;
                end else begin
                    threat_detected = 0;
                end

                asses_timer_start = $realtime;
                next_state = 3; // ASSESS STATE
            end 
        end

        default:begin
            echo_waits = 1;
        end

    endcase
end

always @(posedge scan_for_target) begin
    //$display("SCAN FOR TARGET ", scan_for_target, " ARTAU STATE ", ARTAU_state, " ", next_state, " ", $realtime);
    case(ARTAU_state)

        0:begin // IDLE STATE
            pulse_timer_start = $realtime;
            pulse_counter = 0;
            radar_pulse_trigger = 1;
            #10;
            next_state = 1; // EMIT STATE
        end

        3: begin // ASSESS STATE
            pulse_timer_start = $realtime;
            pulse_counter = 0;
            radar_pulse_trigger = 1;
            #10;
            next_state = 1; // EMIT STATE
        end

    endcase
end

always @(posedge CLK) begin
    ARTAU_state = next_state;
end


always @(innerCLK) begin
    //$display("ALL");
    case(ARTAU_state)
            1:begin 
                if (radar_pulse_trigger) begin
                    if ($realtime - pulse_timer_start >= pulse_time) begin
                        
                        radar_pulse_trigger = 0;
                        pulse_counter = pulse_counter + 1;

                        listen_timer_start = $realtime;
                        distance_start_time = listen_timer_start;
                        
                        next_state = 2; // LISTEN STATE
                        
                    end
                end
            end
            
            2: begin
                
                if ($realtime - listen_timer_start >= listen_time) begin
                    distance_to_target = 0;
                    next_state = 0; // IDLE STATE
                end else begin
                    if (echo_waits) begin
                        echo_trigger = 1;
                    end
                end
            end

            3: begin // ASSESS STATE
                if ($realtime - asses_timer_start >= asses_time) begin
                    distance_to_target = 0;
                    next_state = 0; // IDLE STATE
                end 
            end

        endcase
end

always @(posedge RST) begin
    if (RST) begin
        radar_pulse_trigger = 0;
        distance_to_target = 0;
        threat_detected = 0;
        ARTAU_state = 0;
        next_state = 0;
    end
end


endmodule

src/ICMS.v
`timescale 1us / 1ps

module ICMS(
    input CLK,
    input RST,

    input radar_echo,
    input scan_for_target,
    input [31:0] jet_speed,
    input [31:0] max_safe_distance,
    input [5:0] wind,
    input thunderstorm,
    input [1:0] visibility,
    input signed [7:0] temperature,

    output radar_pulse_trigger,
    output [31:0] distance_to_target,
    output safe_to_engage,
    output threat_detected,
    output emergency_landing_alert,
    output [1:0] ECSU_state,  
    output [1:0] ARTAU_state
);

   // Your code goes here.

    wire severe_weather;

    ARTAU artau(
        .radar_echo(radar_echo),
        .scan_for_target(scan_for_target),
        .jet_speed(jet_speed),
        .max_safe_distance(max_safe_distance),
        .RST(RST),
        .CLK(CLK),
        .radar_pulse_trigger(radar_pulse_trigger),
        .distance_to_target(distance_to_target),
        .threat_detected(threat_detected),
        .ARTAU_state(ARTAU_state)
    );

    ECSU ecsu(
        .wind(wind),
        .thunderstorm(thunderstorm),
        .visibility(visibility),
        .temperature(temperature),
        .RST(RST),
        .CLK(CLK),
        .severe_weather(severe_weather),
        .emergency_landing_alert(emergency_landing_alert),
        .ECSU_state(ECSU_state)
    );

    
assign safe_to_engage = !severe_weather && threat_detected;

endmodule

src/ICMS_tb.v
`timescale 1us / 1ns

module ICMS_tb;

    // Inputs
    reg CLK;
    reg RST;
    reg radar_echo;
    reg scan_for_target;
    reg [31:0] jet_speed;
    reg [31:0] max_safe_distance;
    reg [5:0] wind;
    reg thunderstorm;
    reg [1:0] visibility;
    reg signed [7:0] temperature;
	
    // Outputs
    wire radar_pulse_trigger;
    wire [31:0] distance_to_target;
    wire safe_to_engage;
    wire threat_detected;
    wire emergency_landing_alert;
    wire [1:0] ECSU_state;
    wire [1:0] ARTAU_state;
	
    // Instantiate the Unit Under Test (UUT)
    ICMS uut (
        .CLK(CLK),
        .RST(RST),
        .radar_echo(radar_echo),
        .scan_for_target(scan_for_target),
        .jet_speed(jet_speed),
        .max_safe_distance(max_safe_distance),
        .wind(wind),
        .thunderstorm(thunderstorm),
        .visibility(visibility),
        .temperature(temperature),
        .radar_pulse_trigger(radar_pulse_trigger),
        .distance_to_target(distance_to_target),
        .safe_to_engage(safe_to_engage),
        .threat_detected(threat_detected),
        .emergency_landing_alert(emergency_landing_alert),
        .ECSU_state(ECSU_state),
        .ARTAU_state(ARTAU_state)
    );
	
	// Dump to waveform	 file
    initial begin
        $dumpfile("ICMS.vcd");
        $dumpvars;
    end
	
    // Clock generation
    initial begin
        CLK = 0;
        forever #50 CLK = ~CLK;
    end
	
    initial begin
        // Initialize Inputs
        RST = 1;
        thunderstorm = 0;
        wind = 0;
        visibility = 2'b00;
        temperature = 0;
		
        // Reset the system
        #100;
        RST = 0;
		#200;
		
		// Stimulus
        thunderstorm = 0; wind = 12; visibility = 2'b00; temperature = 25;
        #300;
		thunderstorm = 0; wind = 5; visibility = 2'b00; temperature = 25;
		#300;
		thunderstorm = 0; wind = 5; visibility = 2'b01; temperature = 25;
		#300;
		thunderstorm = 0; wind = 5; visibility = 2'b00; temperature = 25;
		#300;
		thunderstorm = 0; wind = 5; visibility = 2'b01; temperature = 25;
		#300;
		thunderstorm = 1; wind = 5; visibility = 2'b01; temperature = 25;
        #0;
		#300;
		thunderstorm = 0; wind = 5; visibility = 2'b01; temperature = 25;
		#300;
		wind = 3; visibility = 2'b00; temperature = -5;
		#300;
		visibility = 2'b11; 
		#300;
		wind = 25; visibility = 2'b10;
        #500;
		thunderstorm = 0; wind = 0; visibility = 2'b00; temperature = 0; 
		#200;
		
		// Reset the system
		RST = 1;
		#150;
		RST = 0;
		#300;
		
		thunderstorm = 0; wind = 5; visibility = 2'b01; temperature = 25;
		#300;
		thunderstorm = 0; wind = 15; visibility = 2'b01; 
		#30;
		temperature = 40;
        #0;
		#300;
		thunderstorm = 0; wind = 5; visibility = 2'b01; temperature = 25;
		#300;
		thunderstorm = 0; wind = 25; visibility = 2'b01; temperature = -40;
        #0;
		#600;
    end
	
    initial begin
	  
		// Initialize Inputs
	    radar_echo = 0;
        scan_for_target = 0;
        jet_speed = 0;
        max_safe_distance = 0;
        max_safe_distance = 20000;
        jet_speed = 7000;
		
		// Reset the system
        RST = 1;
        #100;
        RST = 0;
        #200;
		
		// Stimulus
        scan_for_target = 1;
        #25;
        scan_for_target = 0;
        #25;
        #250; 
        #50;
        #50;
        radar_echo = 1;
        #2;
        radar_echo = 0;
        #350;
        radar_echo = 1;
        #2;
        radar_echo = 0;
        #98;
        #3100;
        scan_for_target = 1;
        #50;
        scan_for_target = 0;
        #400;
        radar_echo = 1;
        #10;
        radar_echo = 0;
        #500;
        radar_echo = 1;
        #10;
        radar_echo = 0;
        #300;
        scan_for_target = 1;
        #150;
        scan_for_target = 0;
        #2300;
        scan_for_target = 1;
        #50;
        scan_for_target = 0;
        #600;
		
		// Reset the system
        RST=1;
        #100;
        RST=0;
        #100;
		
        $finish; // End the simulation
    end
endmodule

src/ICMS.vcd
$date
	Sun Jan 14 00:09:30 2024
$end
$version
	Icarus Verilog
$end
$timescale
	1ps
$end
$scope module ICMS_tb $end
$var wire 1 ! threat_detected $end
$var wire 1 " safe_to_engage $end
$var wire 1 # radar_pulse_trigger $end
$var wire 1 $ emergency_landing_alert $end
$var wire 32 % distance_to_target [31:0] $end
$var wire 2 & ECSU_state [1:0] $end
$var wire 2 ' ARTAU_state [1:0] $end
$var reg 1 ( CLK $end
$var reg 1 ) RST $end
$var reg 32 * jet_speed [31:0] $end
$var reg 32 + max_safe_distance [31:0] $end
$var reg 1 , radar_echo $end
$var reg 1 - scan_for_target $end
$var reg 8 . temperature [7:0] $end
$var reg 1 / thunderstorm $end
$var reg 2 0 visibility [1:0] $end
$var reg 6 1 wind [5:0] $end
$scope module uut $end
$var wire 1 ( CLK $end
$var wire 1 ) RST $end
$var wire 32 2 jet_speed [31:0] $end
$var wire 32 3 max_safe_distance [31:0] $end
$var wire 1 , radar_echo $end
$var wire 1 " safe_to_engage $end
$var wire 1 - scan_for_target $end
$var wire 8 4 temperature [7:0] $end
$var wire 1 / thunderstorm $end
$var wire 2 5 visibility [1:0] $end
$var wire 6 6 wind [5:0] $end
$var wire 1 ! threat_detected $end
$var wire 1 7 severe_weather $end
$var wire 1 # radar_pulse_trigger $end
$var wire 1 $ emergency_landing_alert $end
$var wire 32 8 distance_to_target [31:0] $end
$var wire 2 9 ECSU_state [1:0] $end
$var wire 2 : ARTAU_state [1:0] $end
$scope module artau $end
$var wire 1 ( CLK $end
$var wire 1 ) RST $end
$var wire 32 ; jet_speed [31:0] $end
$var wire 32 < max_safe_distance [31:0] $end
$var wire 1 , radar_echo $end
$var wire 1 - scan_for_target $end
$var reg 2 = ARTAU_state [1:0] $end
$var reg 32 > asses_time [31:0] $end
$var reg 32 ? asses_timer_start [31:0] $end
$var reg 8 @ clock_time [7:0] $end
$var reg 32 A distance1 [31:0] $end
$var reg 32 B distance2 [31:0] $end
$var reg 32 C distance_end_time [31:0] $end
$var reg 32 D distance_start_time [31:0] $end
$var reg 32 E distance_to_target [31:0] $end
$var reg 1 F echo_trigger $end
$var reg 1 G echo_waits $end
$var reg 32 H first_start_time [31:0] $end
$var reg 1 I innerCLK $end
$var reg 32 J listen_time [31:0] $end
$var reg 32 K listen_timer_start [31:0] $end
$var reg 65 L microsecond [64:0] $end
$var reg 2 M next_state [1:0] $end
$var reg 2 N pulse_counter [1:0] $end
$var reg 32 O pulse_time [31:0] $end
$var reg 32 P pulse_timer_start [31:0] $end
$var reg 1 # radar_pulse_trigger $end
$var reg 33 Q relative_distance [32:0] $end
$var reg 65 R speed_of_light [64:0] $end
$var reg 1 ! threat_detected $end
$upscope $end
$scope module ecsu $end
$var wire 1 ( CLK $end
$var wire 1 ) RST $end
$var wire 8 S temperature [7:0] $end
$var wire 1 / thunderstorm $end
$var wire 2 T visibility [1:0] $end
$var wire 6 U wind [5:0] $end
$var reg 2 V ECSU_state [1:0] $end
$var reg 1 $ emergency_landing_alert $end
$var reg 1 7 severe_weather $end
$upscope $end
$upscope $end
$upscope $end
$enddefinitions $end
$comment Show the parameter values. $end
$dumpall
$end
#0
$dumpvars
b0 V
b0 U
b0 T
b0 S
b10001111000011010001100000000 R
bx Q
bx P
b100101100 O
b0 N
b0 M
b11110100001001000000 L
bx K
b11111010000 J
0I
bx H
xG
xF
b0 E
bx D
bx C
bx B
bx A
b110010 @
bx ?
b101110111000 >
b0 =
b100111000100000 <
b1101101011000 ;
b0 :
b0 9
b0 8
07
b0 6
b0 5
b0 4
b100111000100000 3
b1101101011000 2
b0 1
b0 0
0/
b0 .
0-
0,
b100111000100000 +
b1101101011000 *
1)
0(
b0 '
b0 &
b0 %
0$
0#
0"
0!
$end
#1000000
1I
#2000000
0I
#3000000
1I
#4000000
0I
#5000000
1I
#6000000
0I
#7000000
1I
#8000000
0I
#9000000
1I
#10000000
0I
#11000000
1I
#12000000
0I
#13000000
1I
#14000000
0I
#15000000
1I
#16000000
0I
#17000000
1I
#18000000
0I
#19000000
1I
#20000000
0I
#21000000
1I
#22000000
0I
#23000000
1I
#24000000
0I
#25000000
1I
#26000000
0I
#27000000
1I
#28000000
0I
#29000000
1I
#30000000
0I
#31000000
1I
#32000000
0I
#33000000
1I
#34000000
0I
#35000000
1I
#36000000
0I
#37000000
1I
#38000000
0I
#39000000
1I
#40000000
0I
#41000000
1I
#42000000
0I
#43000000
1I
#44000000
0I
#45000000
1I
#46000000
0I
#47000000
1I
#48000000
0I
#49000000
1I
#50000000
0I
1(
#51000000
1I
#52000000
0I
#53000000
1I
#54000000
0I
#55000000
1I
#56000000
0I
#57000000
1I
#58000000
0I
#59000000
1I
#60000000
0I
#61000000
1I
#62000000
0I
#63000000
1I
#64000000
0I
#65000000
1I
#66000000
0I
#67000000
1I
#68000000
0I
#69000000
1I
#70000000
0I
#71000000
1I
#72000000
0I
#73000000
1I
#74000000
0I
#75000000
1I
#76000000
0I
#77000000
1I
#78000000
0I
#79000000
1I
#80000000
0I
#81000000
1I
#82000000
0I
#83000000
1I
#84000000
0I
#85000000
1I
#86000000
0I
#87000000
1I
#88000000
0I
#89000000
1I
#90000000
0I
#91000000
1I
#92000000
0I
#93000000
1I
#94000000
0I
#95000000
1I
#96000000
0I
#97000000
1I
#98000000
0I
#99000000
1I
#100000000
0I
0(
0)
#101000000
1I
#102000000
0I
#103000000
1I
#104000000
0I
#105000000
1I
#106000000
0I
#107000000
1I
#108000000
0I
#109000000
1I
#110000000
0I
#111000000
1I
#112000000
0I
#113000000
1I
#114000000
0I
#115000000
1I
#116000000
0I
#117000000
1I
#118000000
0I
#119000000
1I
#120000000
0I
#121000000
1I
#122000000
0I
#123000000
1I
#124000000
0I
#125000000
1I
#126000000
0I
#127000000
1I
#128000000
0I
#129000000
1I
#130000000
0I
#131000000
1I
#132000000
0I
#133000000
1I
#134000000
0I
#135000000
1I
#136000000
0I
#137000000
1I
#138000000
0I
#139000000
1I
#140000000
0I
#141000000
1I
#142000000
0I
#143000000
1I
#144000000
0I
#145000000
1I
#146000000
0I
#147000000
1I
#148000000
0I
#149000000
1I
#150000000
0I
1(
#151000000
1I
#152000000
0I
#153000000
1I
#154000000
0I
#155000000
1I
#156000000
0I
#157000000
1I
#158000000
0I
#159000000
1I
#160000000
0I
#161000000
1I
#162000000
0I
#163000000
1I
#164000000
0I
#165000000
1I
#166000000
0I
#167000000
1I
#168000000
0I
#169000000
1I
#170000000
0I
#171000000
1I
#172000000
0I
#173000000
1I
#174000000
0I
#175000000
1I
#176000000
0I
#177000000
1I
#178000000
0I
#179000000
1I
#180000000
0I
#181000000
1I
#182000000
0I
#183000000
1I
#184000000
0I
#185000000
1I
#186000000
0I
#187000000
1I
#188000000
0I
#189000000
1I
#190000000
0I
#191000000
1I
#192000000
0I
#193000000
1I
#194000000
0I
#195000000
1I
#196000000
0I
#197000000
1I
#198000000
0I
#199000000
1I
#200000000
0I
0(
#201000000
1I
#202000000
0I
#203000000
1I
#204000000
0I
#205000000
1I
#206000000
0I
#207000000
1I
#208000000
0I
#209000000
1I
#210000000
0I
#211000000
1I
#212000000
0I
#213000000
1I
#214000000
0I
#215000000
1I
#216000000
0I
#217000000
1I
#218000000
0I
#219000000
1I
#220000000
0I
#221000000
1I
#222000000
0I
#223000000
1I
#224000000
0I
#225000000
1I
#226000000
0I
#227000000
1I
#228000000
0I
#229000000
1I
#230000000
0I
#231000000
1I
#232000000
0I
#233000000
1I
#234000000
0I
#235000000
1I
#236000000
0I
#237000000
1I
#238000000
0I
#239000000
1I
#240000000
0I
#241000000
1I
#242000000
0I
#243000000
1I
#244000000
0I
#245000000
1I
#246000000
0I
#247000000
1I
#248000000
0I
#249000000
1I
#250000000
0I
1(
#251000000
1I
#252000000
0I
#253000000
1I
#254000000
0I
#255000000
1I
#256000000
0I
#257000000
1I
#258000000
0I
#259000000
1I
#260000000
0I
#261000000
1I
#262000000
0I
#263000000
1I
#264000000
0I
#265000000
1I
#266000000
0I
#267000000
1I
#268000000
0I
#269000000
1I
#270000000
0I
#271000000
1I
#272000000
0I
#273000000
1I
#274000000
0I
#275000000
1I
#276000000
0I
#277000000
1I
#278000000
0I
#279000000
1I
#280000000
0I
#281000000
1I
#282000000
0I
#283000000
1I
#284000000
0I
#285000000
1I
#286000000
0I
#287000000
1I
#288000000
0I
#289000000
1I
#290000000
0I
#291000000
1I
#292000000
0I
#293000000
1I
#294000000
0I
#295000000
1I
#296000000
0I
#297000000
1I
#298000000
0I
#299000000
1I
#300000000
1#
b100101100 P
0I
0(
1-
b11001 .
b11001 4
b11001 S
b1100 1
b1100 6
b1100 U
#301000000
1I
#302000000
0I
#303000000
1I
#304000000
0I
#305000000
1I
#306000000
0I
#307000000
1I
#308000000
0I
#309000000
1I
#310000000
0I
b1 M
#311000000
1I
#312000000
0I
#313000000
1I
#314000000
0I
#315000000
1I
#316000000
0I
#317000000
1I
#318000000
0I
#319000000
1I
#320000000
0I
#321000000
1I
#322000000
0I
#323000000
1I
#324000000
0I
#325000000
1I
0-
#326000000
0I
#327000000
1I
#328000000
0I
#329000000
1I
#330000000
0I
#331000000
1I
#332000000
0I
#333000000
1I
#334000000
0I
#335000000
1I
#336000000
0I
#337000000
1I
#338000000
0I
#339000000
1I
#340000000
0I
#341000000
1I
#342000000
0I
#343000000
1I
#344000000
0I
#345000000
1I
#346000000
0I
#347000000
1I
#348000000
0I
#349000000
1I
#350000000
b1 &
b1 9
b1 V
b1 '
b1 :
b1 =
0I
1(
#351000000
1I
#352000000
0I
#353000000
1I
#354000000
0I
#355000000
1I
#356000000
0I
#357000000
1I
#358000000
0I
#359000000
1I
#360000000
0I
#361000000
1I
#362000000
0I
#363000000
1I
#364000000
0I
#365000000
1I
#366000000
0I
#367000000
1I
#368000000
0I
#369000000
1I
#370000000
0I
#371000000
1I
#372000000
0I
#373000000
1I
#374000000
0I
#375000000
1I
#376000000
0I
#377000000
1I
#378000000
0I
#379000000
1I
#380000000
0I
#381000000
1I
#382000000
0I
#383000000
1I
#384000000
0I
#385000000
1I
#386000000
0I
#387000000
1I
#388000000
0I
#389000000
1I
#390000000
0I
#391000000
1I
#392000000
0I
#393000000
1I
#394000000
0I
#395000000
1I
#396000000
0I
#397000000
1I
#398000000
0I
#399000000
1I
#400000000
0I
0(
#401000000
1I
#402000000
0I
#403000000
1I
#404000000
0I
#405000000
1I
#406000000
0I
#407000000
1I
#408000000
0I
#409000000
1I
#410000000
0I
#411000000
1I
#412000000
0I
#413000000
1I
#414000000
0I
#415000000
1I
#416000000
0I
#417000000
1I
#418000000
0I
#419000000
1I
#420000000
0I
#421000000
1I
#422000000
0I
#423000000
1I
#424000000
0I
#425000000
1I
#426000000
0I
#427000000
1I
#428000000
0I
#429000000
1I
#430000000
0I
#431000000
1I
#432000000
0I
#433000000
1I
#434000000
0I
#435000000
1I
#436000000
0I
#437000000
1I
#438000000
0I
#439000000
1I
#440000000
0I
#441000000
1I
#442000000
0I
#443000000
1I
#444000000
0I
#445000000
1I
#446000000
0I
#447000000
1I
#448000000
0I
#449000000
1I
#450000000
0I
1(
#451000000
1I
#452000000
0I
#453000000
1I
#454000000
0I
#455000000
1I
#456000000
0I
#457000000
1I
#458000000
0I
#459000000
1I
#460000000
0I
#461000000
1I
#462000000
0I
#463000000
1I
#464000000
0I
#465000000
1I
#466000000
0I
#467000000
1I
#468000000
0I
#469000000
1I
#470000000
0I
#471000000
1I
#472000000
0I
#473000000
1I
#474000000
0I
#475000000
1I
#476000000
0I
#477000000
1I
#478000000
0I
#479000000
1I
#480000000
0I
#481000000
1I
#482000000
0I
#483000000
1I
#484000000
0I
#485000000
1I
#486000000
0I
#487000000
1I
#488000000
0I
#489000000
1I
#490000000
0I
#491000000
1I
#492000000
0I
#493000000
1I
#494000000
0I
#495000000
1I
#496000000
0I
#497000000
1I
#498000000
0I
#499000000
1I
#500000000
0I
0(
#501000000
1I
#502000000
0I
#503000000
1I
#504000000
0I
#505000000
1I
#506000000
0I
#507000000
1I
#508000000
0I
#509000000
1I
#510000000
0I
#511000000
1I
#512000000
0I
#513000000
1I
#514000000
0I
#515000000
1I
#516000000
0I
#517000000
1I
#518000000
0I
#519000000
1I
#520000000
0I
#521000000
1I
#522000000
0I
#523000000
1I
#524000000
0I
#525000000
1I
#526000000
0I
#527000000
1I
#528000000
0I
#529000000
1I
#530000000
0I
#531000000
1I
#532000000
0I
#533000000
1I
#534000000
0I
#535000000
1I
#536000000
0I
#537000000
1I
#538000000
0I
#539000000
1I
#540000000
0I
#541000000
1I
#542000000
0I
#543000000
1I
#544000000
0I
#545000000
1I
#546000000
0I
#547000000
1I
#548000000
0I
#549000000
1I
#550000000
0I
1(
#551000000
1I
#552000000
0I
#553000000
1I
#554000000
0I
#555000000
1I
#556000000
0I
#557000000
1I
#558000000
0I
#559000000
1I
#560000000
0I
#561000000
1I
#562000000
0I
#563000000
1I
#564000000
0I
#565000000
1I
#566000000
0I
#567000000
1I
#568000000
0I
#569000000
1I
#570000000
0I
#571000000
1I
#572000000
0I
#573000000
1I
#574000000
0I
#575000000
1I
#576000000
0I
#577000000
1I
#578000000
0I
#579000000
1I
#580000000
0I
#581000000
1I
#582000000
0I
#583000000
1I
#584000000
0I
#585000000
1I
#586000000
0I
#587000000
1I
#588000000
0I
#589000000
1I
#590000000
0I
#591000000
1I
#592000000
0I
#593000000
1I
#594000000
0I
#595000000
1I
#596000000
0I
#597000000
1I
#598000000
0I
#599000000
1I
#600000000
b10 M
b1001011000 D
b1001011000 K
b1 N
0#
0I
0(
b101 1
b101 6
b101 U
#601000000
1I
#602000000
0I
#603000000
1I
#604000000
0I
#605000000
1I
#606000000
0I
#607000000
1I
#608000000
0I
#609000000
1I
#610000000
0I
#611000000
1I
#612000000
0I
#613000000
1I
#614000000
0I
#615000000
1I
#616000000
0I
#617000000
1I
#618000000
0I
#619000000
1I
#620000000
0I
#621000000
1I
#622000000
0I
#623000000
1I
#624000000
0I
#625000000
1I
#626000000
0I
#627000000
1I
#628000000
0I
#629000000
1I
#630000000
0I
#631000000
1I
#632000000
0I
#633000000
1I
#634000000
0I
#635000000
1I
#636000000
0I
#637000000
1I
#638000000
0I
#639000000
1I
#640000000
0I
#641000000
1I
#642000000
0I
#643000000
1I
#644000000
0I
#645000000
1I
#646000000
0I
#647000000
1I
#648000000
0I
#649000000
1I
#650000000
b0 &
b0 9
b0 V
b10 '
b10 :
b10 =
0I
1(
